mulankit/__init__.py
mulankit/api.py
mulankit/patch.py
mulankit/app/__init__.py
mulankit/app/meta.json
mulankit/app/samples.txt
mulankit/app/style.css
mulankit/app/webui.py
mulankit/app/viscpm/__init__.py
mulankit/app/viscpm/configuration_cpmbee.py
mulankit/app/viscpm/modeling_cpmbee.py
mulankit/app/viscpm/pipeline_viscpm_paint.py
mulankit/app/viscpm/tokenization_viscpmbee.py
mulankit/internvl/__init__.py
mulankit/internvl/configuration_intern_vit.py
mulankit/internvl/configuration_internvl.py
mulankit/internvl/flash_attention.py
mulankit/internvl/modeling_intern_text.py
mulankit/internvl/modeling_intern_vision.py
mulankit/internvl/modeling_intern_vit.py
mulankit/internvl/modeling_internvl.py
mulankit/internvl/modeling_qllama.py
mulankit/models/__init__.py
mulankit/models/adapter.py
mulankit/models/unet.py
mulankit-1.0.2.dist-info/METADATA
mulankit-1.0.2.dist-info/WHEEL
mulankit-1.0.2.dist-info/top_level.txt
mulankit-1.0.2.dist-info/RECORD
